cv.py
cv-1.0.0.data/scripts/cv
cv-1.0.0.dist-info/LICENSE
cv-1.0.0.dist-info/METADATA
cv-1.0.0.dist-info/WHEEL
cv-1.0.0.dist-info/top_level.txt
cv-1.0.0.dist-info/RECORD
