Metadata-Version: 2.1
Name: cv
Version: 1.0.0
Summary: Check version of a Python module
Home-page: https://github.com/mdrachuk/cv
Author: mdrachuk
Author-email: misha@drach.uk
License: MIT
Project-URL: Pipelines, https://dev.azure.com/misha-drachuk/cv
Project-URL: Source, https://github.com/mdrachuk/cv/
Project-URL: Issues, https://github.com/mdrachuk/cv/issues
Keywords: python packaging version pypi ci
Platform: UNKNOWN
Classifier: Intended Audience :: Developers
Classifier: Topic :: Utilities
Classifier: Development Status :: 3 - Alpha
Classifier: License :: OSI Approved :: MIT License
Classifier: Natural Language :: English
Classifier: Operating System :: MacOS :: MacOS X
Classifier: Operating System :: POSIX
Classifier: Operating System :: POSIX :: BSD
Classifier: Operating System :: POSIX :: Linux
Classifier: Operating System :: Microsoft :: Windows
Classifier: Programming Language :: Python
Classifier: Programming Language :: Python :: 3.7
Classifier: Programming Language :: Python :: Implementation :: CPython
Classifier: Typing :: Typed
Requires-Python: >=3.7
